pklfile/__init__.py
pklfile/pickle.py
pklfile-1.0.2.dist-info/METADATA
pklfile-1.0.2.dist-info/WHEEL
pklfile-1.0.2.dist-info/top_level.txt
pklfile-1.0.2.dist-info/RECORD
